{
  "timestamp": "2026-02-21T18:20:01.141221",
  "checks": [
    {
      "check": "Images",
      "passed": false,
      "issues": [
        "5 cities need images"
      ],
      "fixes": [
        "Image search attempted"
      ],
      "remaining": [
        "Beijing",
        "Shanghai",
        "Chengdu",
        "Harbin",
        "Chongqing"
      ]
    },
    {
      "check": "Pages",
      "passed": false,
      "issues": [
        "5 pages missing"
      ],
      "fixes": [],
      "remaining": [
        "beijing",
        "shanghai",
        "chengdu"
      ]
    },
    {
      "check": "Navigation",
      "passed": false,
      "issues": [
        "Navigation issues detected"
      ],
      "fixes": [
        "Navigation fixes applied"
      ],
      "remaining": []
    },
    {
      "check": "Layout",
      "passed": false,
      "issues": [
        "Missing colors: 2"
      ],
      "fixes": [],
      "remaining": [
        "#2563eb",
        "#1e40af"
      ]
    }
  ],
  "passed": 0,
  "total": 4,
  "message_sent": true
}